{
  "description": "在线点餐小程序",
  "appid": "wx8aa82cf95362aeec",
  "projectname": "dine-app",
  "miniprogramRoot": ".",
  "setting": {
    "urlCheck": true,
    "es6": true,
    "postcss": true,
    "minified": true,
    "newFeature": true,
    "coverView": true,
    "autoAudits": false,
    "showShadowRootInWxmlPanel": true,
    "scopeDataCheck": false,
    "checkInvalidKey": true,
    "checkSiteMap": true,
    "uploadWithSourceMap": true,
    "compileHotReLoad": false,
    "useMultiFrameRuntime": true,
    "useApiHook": true,
    "babelSetting": {
      "ignore": [],
      "disablePlugins": [],
      "outputPath": ""
    },
    "packNpmManually": false,
    "packNpmRelationList": []
  },
  "compileType": "miniprogram",
  "libVersion": "2.25.0",
  "condition": {}
}
